{"id":"ufztr6xlzn1pujdzcf5argo","title":"Airports","desc":"","updated":1652487896038,"created":1636959672643,"custom":{},"fname":"consumer.travel.airports","type":"note","vault":{"fsPath":".","selfContained":true,"name":"notes"},"contentHash":"44acd58175b61cd95a8a764592925035","links":[],"anchors":{"ams":{"type":"header","text":"AMS","value":"ams","line":10,"column":0,"depth":3},"vie":{"type":"header","text":"VIE","value":"vie","line":13,"column":0,"depth":3},"mad":{"type":"header","text":"MAD","value":"mad","line":18,"column":0,"depth":3},"ewr":{"type":"header","text":"EWR","value":"ewr","line":20,"column":0,"depth":3},"lax":{"type":"header","text":"LAX","value":"lax","line":23,"column":0,"depth":3}},"children":[],"parent":"ndat5nbp6paie9ifjyxbqcy","data":{}}
